LICENSE
README.md
setup.py
idc_index_vamsi.egg-info/PKG-INFO
idc_index_vamsi.egg-info/SOURCES.txt
idc_index_vamsi.egg-info/dependency_links.txt
idc_index_vamsi.egg-info/entry_points.txt
idc_index_vamsi.egg-info/requires.txt
idc_index_vamsi.egg-info/top_level.txt
src/__init__.py
src/logic.py
src/main.py