Metadata-Version: 2.1
Name: idc-index-vamsi
Version: 0.0.1
Summary: An application that informs you of the time in different locations and timezones
Home-page: https://vamsithiriveedhi.com
Author: Vamsi Thiriveedhi
Author-email: vamsikrishna1414@gmail.com
License: UNKNOWN
Platform: UNKNOWN
Classifier: Programming Language :: Python :: 3
Classifier: License :: OSI Approved :: MIT License
Classifier: Operating System :: OS Independent
License-File: LICENSE
